pylibmgm-1.1.1.dist-info/RECORD
pylibmgm-1.1.1.dist-info/WHEEL
pylibmgm-1.1.1.dist-info/METADATA
pylibmgm/io.cpython-314-darwin.so
pylibmgm/_pylibmgm.cpython-314-darwin.so
pylibmgm/solver.py
pylibmgm/__init__.pyi
pylibmgm/__init__.py
pylibmgm/solver.pyi
pylibmgm/io.pyi
pylibmgm/.dylibs/libomp.dylib
