Metadata-Version: 2.1
Name: pylibmgm
Version: 1.1.1
Summary: Utilities for graph and multi-graph matching optimization.
Author-Email: Sebastian Stricker <sebastian.stricker@iwr.uni-heidelberg.de>
Classifier: License :: OSI Approved :: GNU General Public License v3 (GPLv3)
Classifier: Operating System :: POSIX :: Linux
Classifier: Programming Language :: C++
Classifier: Programming Language :: Python :: 3
Project-URL: Documentation, https://pylibmgm.readthedocs.io/en/latest/
Project-URL: publication, https://arxiv.org/abs/2406.18215
Project-URL: source, https://github.com/vislearn/multi-matching-optimization
Requires-Python: >=3.10
